[
  {
    "category": "blog",
    "entries": [
      {
        "name": "Test1",
        "file": "/blog/test1.html"
      },
      {
        "name": "page",
        "file": "/blog/page.html"
      },
      {
        "name": "fcc",
        "file": "/blog/gf.html"
      },
      {
        "name": "jhsb",
        "file": "/blog/jhsb.html"
      },
      {
        "name": "sajkbk",
        "file": "/blog/sajkbk.html"
      },
      {
        "name": "m",
        "file": "/blog/m.html"
      }
    ]
  },
  {
    "category": "site",
    "entries": [
      {
        "name": "404",
        "file": "/site/404.html"
      },
      {
        "name": "Index",
        "file": "/site/index.html"
      },
      {
        "name": "Template",
        "file": "/site/template.html"
      }
    ]
  }
]